openapi_client/__init__.py
openapi_client/api_client.py
openapi_client/configuration.py
openapi_client/exceptions.py
openapi_client/rest.py
openapi_client/api/__init__.py
openapi_client/api/api_v1_api.py
openapi_client/models/__init__.py
openapi_client/models/account_invitation_token_validate_response.py
openapi_client/models/account_sign_in_cli_check_response.py
openapi_client/models/account_sign_in_cli_token_response.py
openapi_client/models/account_ssh_key_list_response.py
openapi_client/models/change_password_api_payload.py
openapi_client/models/change_username_api_payload.py
openapi_client/models/cli_experiment_freeze_dataset_version_api_payload.py
openapi_client/models/cli_experiment_plots_files_update_api_payload.py
openapi_client/models/cli_experiment_plots_metrics_update_api_payload.py
openapi_client/models/cli_project_create_api_payload.py
openapi_client/models/cluster_all_cluster_list_response.py
openapi_client/models/cluster_custom_cluster_experiment_list_response.py
openapi_client/models/cluster_custom_cluster_key_response.py
openapi_client/models/cluster_custom_cluster_list_response.py
openapi_client/models/cluster_custom_cluster_node_list_response.py
openapi_client/models/custom_cluster_add_api_payload.py
openapi_client/models/custom_cluster_update_api_payload.py
openapi_client/models/dashboard_dashboard_experiment_field_list_response.py
openapi_client/models/dashboard_dashboard_experiment_field_update_response.py
openapi_client/models/dashboard_dashboard_experiment_field_value_list_response.py
openapi_client/models/dashboard_dashboard_experiment_list_response.py
openapi_client/models/dashboard_experiment_field_update_api_payload.py
openapi_client/models/dashboard_experiment_filter_create_api_payload.py
openapi_client/models/dashboard_experiment_filter_update_api_payload.py
openapi_client/models/dashboard_experiment_sort_create_api_payload.py
openapi_client/models/dashboard_experiment_sort_update_api_payload.py
savvihub-0.1.18.dist-info/LICENSE
savvihub-0.1.18.dist-info/METADATA
savvihub-0.1.18.dist-info/WHEEL
savvihub-0.1.18.dist-info/entry_points.txt
savvihub-0.1.18.dist-info/top_level.txt
savvihub-0.1.18.dist-info/RECORD
